Organizze_Wrapper/API.py
Organizze_Wrapper/CartoesCredito.py
Organizze_Wrapper/Categorias.py
Organizze_Wrapper/Contas.py
Organizze_Wrapper/FaturasCartao.py
Organizze_Wrapper/Lancamentos.py
Organizze_Wrapper/Metas.py
Organizze_Wrapper/Usuarios.py
Organizze_Wrapper/__init__.py
Organizze_Wrapper-1.3.2.dist-info/LICENSE
Organizze_Wrapper-1.3.2.dist-info/METADATA
Organizze_Wrapper-1.3.2.dist-info/WHEEL
Organizze_Wrapper-1.3.2.dist-info/top_level.txt
Organizze_Wrapper-1.3.2.dist-info/RECORD
