Metadata-Version: 2.1
Name: Organizze_Wrapper
Version: 1.3.2
Summary: Biblioteca Python de Wrapper para a API do Organizze.com.br
Home-page: https://github.com/anderbytes/Organizze-Wrapper
Author: Anderson
Author-email: anderbytes@gmail.com
License-File: LICENSE
Requires-Dist: requests >=2.32.3
Requires-Dist: PyMultiHelper >=1.1.11
Requires-Dist: pandas >=2.2.3
